xmatters/__init__.py
xmatters/auth.py
xmatters/connection.py
xmatters/endpoints.py
xmatters/errors.py
xmatters/factories.py
xmatters/session.py
xmatters/utils.py
xmatters/objects/__init__.py
xmatters/objects/attachments.py
xmatters/objects/audits.py
xmatters/objects/common.py
xmatters/objects/conference_bridges.py
xmatters/objects/device_names.py
xmatters/objects/device_types.py
xmatters/objects/devices.py
xmatters/objects/dynamic_teams.py
xmatters/objects/event_suppressions.py
xmatters/objects/events.py
xmatters/objects/forms.py
xmatters/objects/groups.py
xmatters/objects/imports.py
xmatters/objects/incidents.py
xmatters/objects/integrations.py
xmatters/objects/oncall.py
xmatters/objects/oncall_summary.py
xmatters/objects/people.py
xmatters/objects/plan_constants.py
xmatters/objects/plan_endpoints.py
xmatters/objects/plan_properties.py
xmatters/objects/plans.py
xmatters/objects/roles.py
xmatters/objects/scenarios.py
xmatters/objects/services.py
xmatters/objects/shared_libraries.py
xmatters/objects/shifts.py
xmatters/objects/sites.py
xmatters/objects/subscription_forms.py
xmatters/objects/subscriptions.py
xmatters/objects/temporary_absences.py
python_xmatters-1.1.1.dist-info/LICENSE
python_xmatters-1.1.1.dist-info/METADATA
python_xmatters-1.1.1.dist-info/WHEEL
python_xmatters-1.1.1.dist-info/top_level.txt
python_xmatters-1.1.1.dist-info/RECORD
