Metadata-Version: 2.1
Name: python-xmatters
Version: 1.1.1
Summary: Python xMatters API wrapper
Home-page: https://github.com/hcallen/python-xmatters
Author: hcallen
Author-email: hallieallen@gmail.com
Maintainer: hcallen
Maintainer-email: hallieallen@gmail.com
License: MIT
Platform: UNKNOWN
Classifier: Development Status :: 4 - Beta
Classifier: Intended Audience :: Developers
Classifier: License :: OSI Approved :: MIT License
Classifier: Topic :: System :: Monitoring
Classifier: Topic :: Software Development :: Libraries
Classifier: Topic :: Communications
Classifier: Programming Language :: Python
Classifier: Programming Language :: Python :: 3 :: Only
Classifier: Programming Language :: Python :: 3.5
Classifier: Programming Language :: Python :: 3.6
Classifier: Programming Language :: Python :: 3.7
Classifier: Programming Language :: Python :: 3.8
Classifier: Programming Language :: Python :: 3.9
Classifier: Operating System :: OS Independent
Requires-Python: >=3.5
License-File: LICENSE
Requires-Dist: certifi (>=2021.10.8)
Requires-Dist: charset-normalizer (>=2.0.11)
Requires-Dist: idna (>=3.3)
Requires-Dist: oauthlib (>=3.2.0)
Requires-Dist: python-dateutil (>=2.8.2)
Requires-Dist: requests (>=2.27.1)
Requires-Dist: requests-oauthlib (>=1.3.1)
Requires-Dist: six (>=1.16.0)
Requires-Dist: urllib3 (>=1.26.8)
